.source GCTest.btm
.class public A
.super java/lang/Object
.implements java/lang/Cloneable

.field protected a0 I
.field protected a1 I
.field protected a2 I
.field protected a3 I
.field protected a4 I
.field protected a5 I
.field protected a6 I
.field protected a7 I
.field protected a8 I
.field protected a9 I
.field protected a10 I
.field protected a11 I
.field protected a12 I
.field protected a13 I
.field protected a14 I
.field protected a15 I
.field protected a16 I
.field protected a17 I
.field protected a18 I
.field protected a19 I
.field protected a20 I
.field protected a21 I
.field protected a22 I
.field protected a23 I
.field protected a24 I
.field protected a25 I
.field protected a26 I
.field protected a27 I
.field protected a28 I
.field protected a29 I
.field protected a30 I
.field protected a31 I
.field protected a32 I
.field protected a33 I
.field protected a34 I
.field protected a35 I
.field protected a36 I
.field protected a37 I
.field protected a38 I
.field protected a39 I
.field protected a40 I
.field protected a41 I
.field protected a42 I
.field protected a43 I
.field protected a44 I
.field protected a45 I
.field protected a46 I
.field protected a47 I
.field protected a48 I
.field protected a49 I
.field protected a50 I
.field protected a51 I
.field protected a52 I
.field protected a53 I
.field protected a54 I
.field protected a55 I
.field protected a56 I
.field protected a57 I
.field protected a58 I
.field protected a59 I
.field protected a60 I
.field protected a61 I
.field protected a62 I
.field protected a63 I
.field protected a64 I
.field protected a65 I
.field protected a66 I
.field protected a67 I
.field protected a68 I
.field protected a69 I
.field protected a70 I
.field protected a71 I
.field protected a72 I
.field protected a73 I
.field protected a74 I
.field protected a75 I
.field protected a76 I
.field protected a77 I
.field protected a78 I
.field protected a79 I
.field protected a80 I
.field protected a81 I
.field protected a82 I
.field protected a83 I
.field protected a84 I
.field protected a85 I
.field protected a86 I
.field protected a87 I
.field protected a88 I
.field protected a89 I
.field protected a90 I
.field protected a91 I
.field protected a92 I
.field protected a93 I
.field protected a94 I
.field protected a95 I
.field protected a96 I
.field protected a97 I
.field protected a98 I
.field protected a99 I
.field protected a100 I
.field protected a101 I
.field protected a102 I
.field protected a103 I
.field protected a104 I
.field protected a105 I
.field protected a106 I
.field protected a107 I
.field protected a108 I
.field protected a109 I
.field protected a110 I
.field protected a111 I
.field protected a112 I
.field protected a113 I
.field protected a114 I
.field protected a115 I
.field protected a116 I
.field protected a117 I
.field protected a118 I
.field protected a119 I
.field protected a120 I
.field protected a121 I
.field protected a122 I
.field protected a123 I
.field protected a124 I
.field protected a125 I
.field protected a126 I
.field protected a127 I
.field protected a128 I
.field protected a129 I
.field protected a130 I
.field protected a131 I
.field protected a132 I
.field protected a133 I
.field protected a134 I
.field protected a135 I
.field protected a136 I
.field protected a137 I
.field protected a138 I
.field protected a139 I
.field protected a140 I
.field protected a141 I
.field protected a142 I
.field protected a143 I
.field protected a144 I
.field protected a145 I
.field protected a146 I
.field protected a147 I
.field protected a148 I
.field protected a149 I
.field protected a150 I
.field protected a151 I
.field protected a152 I
.field protected a153 I
.field protected a154 I
.field protected a155 I
.field protected a156 I
.field protected a157 I
.field protected a158 I
.field protected a159 I
.field protected a160 I
.field protected a161 I
.field protected a162 I
.field protected a163 I
.field protected a164 I
.field protected a165 I
.field protected a166 I
.field protected a167 I
.field protected a168 I
.field protected a169 I
.field protected a170 I
.field protected a171 I
.field protected a172 I
.field protected a173 I
.field protected a174 I
.field protected a175 I
.field protected a176 I
.field protected a177 I
.field protected a178 I
.field protected a179 I
.field protected a180 I
.field protected a181 I
.field protected a182 I
.field protected a183 I
.field protected a184 I
.field protected a185 I
.field protected a186 I
.field protected a187 I
.field protected a188 I
.field protected a189 I
.field protected a190 I
.field protected a191 I
.field protected a192 I
.field protected a193 I
.field protected a194 I
.field protected a195 I
.field protected a196 I
.field protected a197 I
.field protected a198 I
.field protected a199 I
.field protected a200 I
.field protected a201 I
.field protected a202 I
.field protected a203 I
.field protected a204 I
.field protected a205 I
.field protected a206 I
.field protected a207 I
.field protected a208 I
.field protected a209 I
.field protected a210 I
.field protected a211 I
.field protected a212 I
.field protected a213 I
.field protected a214 I
.field protected a215 I
.field protected a216 I
.field protected a217 I
.field protected a218 I
.field protected a219 I
.field protected a220 I
.field protected a221 I
.field protected a222 I
.field protected a223 I
.field protected a224 I
.field protected a225 I
.field protected a226 I
.field protected a227 I
.field protected a228 I
.field protected a229 I
.field protected a230 I
.field protected a231 I
.field protected a232 I
.field protected a233 I
.field protected a234 I
.field protected a235 I
.field protected a236 I
.field protected a237 I
.field protected a238 I
.field protected a239 I
.field protected a240 I
.field protected a241 I
.field protected a242 I
.field protected a243 I
.field protected a244 I
.field protected a245 I
.field protected a246 I
.field protected a247 I
.field protected a248 I
.field protected a249 I
.field protected a250 I
.field protected a251 I
.field protected a252 I
.field protected a253 I
.field protected a254 I
.field protected a255 I
.field protected a256 I
.field protected a257 I
.field protected a258 I
.field protected a259 I
.field protected a260 I
.field protected a261 I
.field protected a262 I
.field protected a263 I
.field protected a264 I
.field protected a265 I
.field protected a266 I
.field protected a267 I
.field protected a268 I
.field protected a269 I
.field protected a270 I
.field protected a271 I
.field protected a272 I
.field protected a273 I
.field protected a274 I
.field protected a275 I
.field protected a276 I
.field protected a277 I
.field protected a278 I
.field protected a279 I
.field protected a280 I
.field protected a281 I
.field protected a282 I
.field protected a283 I
.field protected a284 I
.field protected a285 I
.field protected a286 I
.field protected a287 I
.field protected a288 I
.field protected a289 I
.field protected a290 I
.field protected a291 I
.field protected a292 I
.field protected a293 I
.field protected a294 I
.field protected a295 I
.field protected a296 I
.field protected a297 I
.field protected a298 I
.field protected a299 I
.field protected a300 I
.field protected a301 I
.field protected a302 I
.field protected a303 I
.field protected a304 I
.field protected a305 I
.field protected a306 I
.field protected a307 I
.field protected a308 I
.field protected a309 I
.field protected a310 I
.field protected a311 I
.field protected a312 I
.field protected a313 I
.field protected a314 I
.field protected a315 I
.field protected a316 I
.field protected a317 I
.field protected a318 I
.field protected a319 I
.field protected a320 I
.field protected a321 I
.field protected a322 I
.field protected a323 I
.field protected a324 I
.field protected a325 I
.field protected a326 I
.field protected a327 I
.field protected a328 I
.field protected a329 I
.field protected a330 I
.field protected a331 I
.field protected a332 I
.field protected a333 I
.field protected a334 I
.field protected a335 I
.field protected a336 I
.field protected a337 I
.field protected a338 I
.field protected a339 I
.field protected a340 I
.field protected a341 I
.field protected a342 I
.field protected a343 I
.field protected a344 I
.field protected a345 I
.field protected a346 I
.field protected a347 I
.field protected a348 I
.field protected a349 I
.field protected a350 I
.field protected a351 I
.field protected a352 I
.field protected a353 I
.field protected a354 I
.field protected a355 I
.field protected a356 I
.field protected a357 I
.field protected a358 I
.field protected a359 I
.field protected a360 I
.field protected a361 I
.field protected a362 I
.field protected a363 I
.field protected a364 I
.field protected a365 I
.field protected a366 I
.field protected a367 I
.field protected a368 I
.field protected a369 I
.field protected a370 I
.field protected a371 I
.field protected a372 I
.field protected a373 I
.field protected a374 I
.field protected a375 I
.field protected a376 I
.field protected a377 I
.field protected a378 I
.field protected a379 I
.field protected a380 I
.field protected a381 I
.field protected a382 I
.field protected a383 I
.field protected a384 I
.field protected a385 I
.field protected a386 I
.field protected a387 I
.field protected a388 I
.field protected a389 I
.field protected a390 I
.field protected a391 I
.field protected a392 I
.field protected a393 I
.field protected a394 I
.field protected a395 I
.field protected a396 I
.field protected a397 I
.field protected a398 I
.field protected a399 I
.field protected a400 I
.field protected a401 I
.field protected a402 I
.field protected a403 I
.field protected a404 I
.field protected a405 I
.field protected a406 I
.field protected a407 I
.field protected a408 I
.field protected a409 I
.field protected a410 I
.field protected a411 I
.field protected a412 I
.field protected a413 I
.field protected a414 I
.field protected a415 I
.field protected a416 I
.field protected a417 I
.field protected a418 I
.field protected a419 I
.field protected a420 I
.field protected a421 I
.field protected a422 I
.field protected a423 I
.field protected a424 I
.field protected a425 I
.field protected a426 I
.field protected a427 I
.field protected a428 I
.field protected a429 I
.field protected a430 I
.field protected a431 I
.field protected a432 I
.field protected a433 I
.field protected a434 I
.field protected a435 I
.field protected a436 I
.field protected a437 I
.field protected a438 I
.field protected a439 I
.field protected a440 I
.field protected a441 I
.field protected a442 I
.field protected a443 I
.field protected a444 I
.field protected a445 I
.field protected a446 I
.field protected a447 I
.field protected a448 I
.field protected a449 I
.field protected a450 I
.field protected a451 I
.field protected a452 I
.field protected a453 I
.field protected a454 I
.field protected a455 I
.field protected a456 I
.field protected a457 I
.field protected a458 I
.field protected a459 I
.field protected a460 I
.field protected a461 I
.field protected a462 I
.field protected a463 I
.field protected a464 I
.field protected a465 I
.field protected a466 I
.field protected a467 I
.field protected a468 I
.field protected a469 I
.field protected a470 I
.field protected a471 I
.field protected a472 I
.field protected a473 I
.field protected a474 I
.field protected a475 I
.field protected a476 I
.field protected a477 I
.field protected a478 I
.field protected a479 I
.field protected a480 I
.field protected a481 I
.field protected a482 I
.field protected a483 I
.field protected a484 I
.field protected a485 I
.field protected a486 I
.field protected a487 I
.field protected a488 I
.field protected a489 I
.field protected a490 I
.field protected a491 I
.field protected a492 I
.field protected a493 I
.field protected a494 I
.field protected a495 I
.field protected a496 I
.field protected a497 I
.field protected a498 I
.field protected a499 I

; A constructor
.method public <init>()V
	.limit stack 3
	.limit locals 1
	aload_0
	dup
	invokespecial java/lang/Object/<init>()V 

	; field initialization: a0
	aload_0
	iconst_0
	putfield A/a0 I 

	; field initialization: a1
	aload_0
	iconst_0
	putfield A/a1 I 

	; field initialization: a2
	aload_0
	iconst_0
	putfield A/a2 I 

	; field initialization: a3
	aload_0
	iconst_0
	putfield A/a3 I 

	; field initialization: a4
	aload_0
	iconst_0
	putfield A/a4 I 

	; field initialization: a5
	aload_0
	iconst_0
	putfield A/a5 I 

	; field initialization: a6
	aload_0
	iconst_0
	putfield A/a6 I 

	; field initialization: a7
	aload_0
	iconst_0
	putfield A/a7 I 

	; field initialization: a8
	aload_0
	iconst_0
	putfield A/a8 I 

	; field initialization: a9
	aload_0
	iconst_0
	putfield A/a9 I 

	; field initialization: a10
	aload_0
	iconst_0
	putfield A/a10 I 

	; field initialization: a11
	aload_0
	iconst_0
	putfield A/a11 I 

	; field initialization: a12
	aload_0
	iconst_0
	putfield A/a12 I 

	; field initialization: a13
	aload_0
	iconst_0
	putfield A/a13 I 

	; field initialization: a14
	aload_0
	iconst_0
	putfield A/a14 I 

	; field initialization: a15
	aload_0
	iconst_0
	putfield A/a15 I 

	; field initialization: a16
	aload_0
	iconst_0
	putfield A/a16 I 

	; field initialization: a17
	aload_0
	iconst_0
	putfield A/a17 I 

	; field initialization: a18
	aload_0
	iconst_0
	putfield A/a18 I 

	; field initialization: a19
	aload_0
	iconst_0
	putfield A/a19 I 

	; field initialization: a20
	aload_0
	iconst_0
	putfield A/a20 I 

	; field initialization: a21
	aload_0
	iconst_0
	putfield A/a21 I 

	; field initialization: a22
	aload_0
	iconst_0
	putfield A/a22 I 

	; field initialization: a23
	aload_0
	iconst_0
	putfield A/a23 I 

	; field initialization: a24
	aload_0
	iconst_0
	putfield A/a24 I 

	; field initialization: a25
	aload_0
	iconst_0
	putfield A/a25 I 

	; field initialization: a26
	aload_0
	iconst_0
	putfield A/a26 I 

	; field initialization: a27
	aload_0
	iconst_0
	putfield A/a27 I 

	; field initialization: a28
	aload_0
	iconst_0
	putfield A/a28 I 

	; field initialization: a29
	aload_0
	iconst_0
	putfield A/a29 I 

	; field initialization: a30
	aload_0
	iconst_0
	putfield A/a30 I 

	; field initialization: a31
	aload_0
	iconst_0
	putfield A/a31 I 

	; field initialization: a32
	aload_0
	iconst_0
	putfield A/a32 I 

	; field initialization: a33
	aload_0
	iconst_0
	putfield A/a33 I 

	; field initialization: a34
	aload_0
	iconst_0
	putfield A/a34 I 

	; field initialization: a35
	aload_0
	iconst_0
	putfield A/a35 I 

	; field initialization: a36
	aload_0
	iconst_0
	putfield A/a36 I 

	; field initialization: a37
	aload_0
	iconst_0
	putfield A/a37 I 

	; field initialization: a38
	aload_0
	iconst_0
	putfield A/a38 I 

	; field initialization: a39
	aload_0
	iconst_0
	putfield A/a39 I 

	; field initialization: a40
	aload_0
	iconst_0
	putfield A/a40 I 

	; field initialization: a41
	aload_0
	iconst_0
	putfield A/a41 I 

	; field initialization: a42
	aload_0
	iconst_0
	putfield A/a42 I 

	; field initialization: a43
	aload_0
	iconst_0
	putfield A/a43 I 

	; field initialization: a44
	aload_0
	iconst_0
	putfield A/a44 I 

	; field initialization: a45
	aload_0
	iconst_0
	putfield A/a45 I 

	; field initialization: a46
	aload_0
	iconst_0
	putfield A/a46 I 

	; field initialization: a47
	aload_0
	iconst_0
	putfield A/a47 I 

	; field initialization: a48
	aload_0
	iconst_0
	putfield A/a48 I 

	; field initialization: a49
	aload_0
	iconst_0
	putfield A/a49 I 

	; field initialization: a50
	aload_0
	iconst_0
	putfield A/a50 I 

	; field initialization: a51
	aload_0
	iconst_0
	putfield A/a51 I 

	; field initialization: a52
	aload_0
	iconst_0
	putfield A/a52 I 

	; field initialization: a53
	aload_0
	iconst_0
	putfield A/a53 I 

	; field initialization: a54
	aload_0
	iconst_0
	putfield A/a54 I 

	; field initialization: a55
	aload_0
	iconst_0
	putfield A/a55 I 

	; field initialization: a56
	aload_0
	iconst_0
	putfield A/a56 I 

	; field initialization: a57
	aload_0
	iconst_0
	putfield A/a57 I 

	; field initialization: a58
	aload_0
	iconst_0
	putfield A/a58 I 

	; field initialization: a59
	aload_0
	iconst_0
	putfield A/a59 I 

	; field initialization: a60
	aload_0
	iconst_0
	putfield A/a60 I 

	; field initialization: a61
	aload_0
	iconst_0
	putfield A/a61 I 

	; field initialization: a62
	aload_0
	iconst_0
	putfield A/a62 I 

	; field initialization: a63
	aload_0
	iconst_0
	putfield A/a63 I 

	; field initialization: a64
	aload_0
	iconst_0
	putfield A/a64 I 

	; field initialization: a65
	aload_0
	iconst_0
	putfield A/a65 I 

	; field initialization: a66
	aload_0
	iconst_0
	putfield A/a66 I 

	; field initialization: a67
	aload_0
	iconst_0
	putfield A/a67 I 

	; field initialization: a68
	aload_0
	iconst_0
	putfield A/a68 I 

	; field initialization: a69
	aload_0
	iconst_0
	putfield A/a69 I 

	; field initialization: a70
	aload_0
	iconst_0
	putfield A/a70 I 

	; field initialization: a71
	aload_0
	iconst_0
	putfield A/a71 I 

	; field initialization: a72
	aload_0
	iconst_0
	putfield A/a72 I 

	; field initialization: a73
	aload_0
	iconst_0
	putfield A/a73 I 

	; field initialization: a74
	aload_0
	iconst_0
	putfield A/a74 I 

	; field initialization: a75
	aload_0
	iconst_0
	putfield A/a75 I 

	; field initialization: a76
	aload_0
	iconst_0
	putfield A/a76 I 

	; field initialization: a77
	aload_0
	iconst_0
	putfield A/a77 I 

	; field initialization: a78
	aload_0
	iconst_0
	putfield A/a78 I 

	; field initialization: a79
	aload_0
	iconst_0
	putfield A/a79 I 

	; field initialization: a80
	aload_0
	iconst_0
	putfield A/a80 I 

	; field initialization: a81
	aload_0
	iconst_0
	putfield A/a81 I 

	; field initialization: a82
	aload_0
	iconst_0
	putfield A/a82 I 

	; field initialization: a83
	aload_0
	iconst_0
	putfield A/a83 I 

	; field initialization: a84
	aload_0
	iconst_0
	putfield A/a84 I 

	; field initialization: a85
	aload_0
	iconst_0
	putfield A/a85 I 

	; field initialization: a86
	aload_0
	iconst_0
	putfield A/a86 I 

	; field initialization: a87
	aload_0
	iconst_0
	putfield A/a87 I 

	; field initialization: a88
	aload_0
	iconst_0
	putfield A/a88 I 

	; field initialization: a89
	aload_0
	iconst_0
	putfield A/a89 I 

	; field initialization: a90
	aload_0
	iconst_0
	putfield A/a90 I 

	; field initialization: a91
	aload_0
	iconst_0
	putfield A/a91 I 

	; field initialization: a92
	aload_0
	iconst_0
	putfield A/a92 I 

	; field initialization: a93
	aload_0
	iconst_0
	putfield A/a93 I 

	; field initialization: a94
	aload_0
	iconst_0
	putfield A/a94 I 

	; field initialization: a95
	aload_0
	iconst_0
	putfield A/a95 I 

	; field initialization: a96
	aload_0
	iconst_0
	putfield A/a96 I 

	; field initialization: a97
	aload_0
	iconst_0
	putfield A/a97 I 

	; field initialization: a98
	aload_0
	iconst_0
	putfield A/a98 I 

	; field initialization: a99
	aload_0
	iconst_0
	putfield A/a99 I 

	; field initialization: a100
	aload_0
	iconst_0
	putfield A/a100 I 

	; field initialization: a101
	aload_0
	iconst_0
	putfield A/a101 I 

	; field initialization: a102
	aload_0
	iconst_0
	putfield A/a102 I 

	; field initialization: a103
	aload_0
	iconst_0
	putfield A/a103 I 

	; field initialization: a104
	aload_0
	iconst_0
	putfield A/a104 I 

	; field initialization: a105
	aload_0
	iconst_0
	putfield A/a105 I 

	; field initialization: a106
	aload_0
	iconst_0
	putfield A/a106 I 

	; field initialization: a107
	aload_0
	iconst_0
	putfield A/a107 I 

	; field initialization: a108
	aload_0
	iconst_0
	putfield A/a108 I 

	; field initialization: a109
	aload_0
	iconst_0
	putfield A/a109 I 

	; field initialization: a110
	aload_0
	iconst_0
	putfield A/a110 I 

	; field initialization: a111
	aload_0
	iconst_0
	putfield A/a111 I 

	; field initialization: a112
	aload_0
	iconst_0
	putfield A/a112 I 

	; field initialization: a113
	aload_0
	iconst_0
	putfield A/a113 I 

	; field initialization: a114
	aload_0
	iconst_0
	putfield A/a114 I 

	; field initialization: a115
	aload_0
	iconst_0
	putfield A/a115 I 

	; field initialization: a116
	aload_0
	iconst_0
	putfield A/a116 I 

	; field initialization: a117
	aload_0
	iconst_0
	putfield A/a117 I 

	; field initialization: a118
	aload_0
	iconst_0
	putfield A/a118 I 

	; field initialization: a119
	aload_0
	iconst_0
	putfield A/a119 I 

	; field initialization: a120
	aload_0
	iconst_0
	putfield A/a120 I 

	; field initialization: a121
	aload_0
	iconst_0
	putfield A/a121 I 

	; field initialization: a122
	aload_0
	iconst_0
	putfield A/a122 I 

	; field initialization: a123
	aload_0
	iconst_0
	putfield A/a123 I 

	; field initialization: a124
	aload_0
	iconst_0
	putfield A/a124 I 

	; field initialization: a125
	aload_0
	iconst_0
	putfield A/a125 I 

	; field initialization: a126
	aload_0
	iconst_0
	putfield A/a126 I 

	; field initialization: a127
	aload_0
	iconst_0
	putfield A/a127 I 

	; field initialization: a128
	aload_0
	iconst_0
	putfield A/a128 I 

	; field initialization: a129
	aload_0
	iconst_0
	putfield A/a129 I 

	; field initialization: a130
	aload_0
	iconst_0
	putfield A/a130 I 

	; field initialization: a131
	aload_0
	iconst_0
	putfield A/a131 I 

	; field initialization: a132
	aload_0
	iconst_0
	putfield A/a132 I 

	; field initialization: a133
	aload_0
	iconst_0
	putfield A/a133 I 

	; field initialization: a134
	aload_0
	iconst_0
	putfield A/a134 I 

	; field initialization: a135
	aload_0
	iconst_0
	putfield A/a135 I 

	; field initialization: a136
	aload_0
	iconst_0
	putfield A/a136 I 

	; field initialization: a137
	aload_0
	iconst_0
	putfield A/a137 I 

	; field initialization: a138
	aload_0
	iconst_0
	putfield A/a138 I 

	; field initialization: a139
	aload_0
	iconst_0
	putfield A/a139 I 

	; field initialization: a140
	aload_0
	iconst_0
	putfield A/a140 I 

	; field initialization: a141
	aload_0
	iconst_0
	putfield A/a141 I 

	; field initialization: a142
	aload_0
	iconst_0
	putfield A/a142 I 

	; field initialization: a143
	aload_0
	iconst_0
	putfield A/a143 I 

	; field initialization: a144
	aload_0
	iconst_0
	putfield A/a144 I 

	; field initialization: a145
	aload_0
	iconst_0
	putfield A/a145 I 

	; field initialization: a146
	aload_0
	iconst_0
	putfield A/a146 I 

	; field initialization: a147
	aload_0
	iconst_0
	putfield A/a147 I 

	; field initialization: a148
	aload_0
	iconst_0
	putfield A/a148 I 

	; field initialization: a149
	aload_0
	iconst_0
	putfield A/a149 I 

	; field initialization: a150
	aload_0
	iconst_0
	putfield A/a150 I 

	; field initialization: a151
	aload_0
	iconst_0
	putfield A/a151 I 

	; field initialization: a152
	aload_0
	iconst_0
	putfield A/a152 I 

	; field initialization: a153
	aload_0
	iconst_0
	putfield A/a153 I 

	; field initialization: a154
	aload_0
	iconst_0
	putfield A/a154 I 

	; field initialization: a155
	aload_0
	iconst_0
	putfield A/a155 I 

	; field initialization: a156
	aload_0
	iconst_0
	putfield A/a156 I 

	; field initialization: a157
	aload_0
	iconst_0
	putfield A/a157 I 

	; field initialization: a158
	aload_0
	iconst_0
	putfield A/a158 I 

	; field initialization: a159
	aload_0
	iconst_0
	putfield A/a159 I 

	; field initialization: a160
	aload_0
	iconst_0
	putfield A/a160 I 

	; field initialization: a161
	aload_0
	iconst_0
	putfield A/a161 I 

	; field initialization: a162
	aload_0
	iconst_0
	putfield A/a162 I 

	; field initialization: a163
	aload_0
	iconst_0
	putfield A/a163 I 

	; field initialization: a164
	aload_0
	iconst_0
	putfield A/a164 I 

	; field initialization: a165
	aload_0
	iconst_0
	putfield A/a165 I 

	; field initialization: a166
	aload_0
	iconst_0
	putfield A/a166 I 

	; field initialization: a167
	aload_0
	iconst_0
	putfield A/a167 I 

	; field initialization: a168
	aload_0
	iconst_0
	putfield A/a168 I 

	; field initialization: a169
	aload_0
	iconst_0
	putfield A/a169 I 

	; field initialization: a170
	aload_0
	iconst_0
	putfield A/a170 I 

	; field initialization: a171
	aload_0
	iconst_0
	putfield A/a171 I 

	; field initialization: a172
	aload_0
	iconst_0
	putfield A/a172 I 

	; field initialization: a173
	aload_0
	iconst_0
	putfield A/a173 I 

	; field initialization: a174
	aload_0
	iconst_0
	putfield A/a174 I 

	; field initialization: a175
	aload_0
	iconst_0
	putfield A/a175 I 

	; field initialization: a176
	aload_0
	iconst_0
	putfield A/a176 I 

	; field initialization: a177
	aload_0
	iconst_0
	putfield A/a177 I 

	; field initialization: a178
	aload_0
	iconst_0
	putfield A/a178 I 

	; field initialization: a179
	aload_0
	iconst_0
	putfield A/a179 I 

	; field initialization: a180
	aload_0
	iconst_0
	putfield A/a180 I 

	; field initialization: a181
	aload_0
	iconst_0
	putfield A/a181 I 

	; field initialization: a182
	aload_0
	iconst_0
	putfield A/a182 I 

	; field initialization: a183
	aload_0
	iconst_0
	putfield A/a183 I 

	; field initialization: a184
	aload_0
	iconst_0
	putfield A/a184 I 

	; field initialization: a185
	aload_0
	iconst_0
	putfield A/a185 I 

	; field initialization: a186
	aload_0
	iconst_0
	putfield A/a186 I 

	; field initialization: a187
	aload_0
	iconst_0
	putfield A/a187 I 

	; field initialization: a188
	aload_0
	iconst_0
	putfield A/a188 I 

	; field initialization: a189
	aload_0
	iconst_0
	putfield A/a189 I 

	; field initialization: a190
	aload_0
	iconst_0
	putfield A/a190 I 

	; field initialization: a191
	aload_0
	iconst_0
	putfield A/a191 I 

	; field initialization: a192
	aload_0
	iconst_0
	putfield A/a192 I 

	; field initialization: a193
	aload_0
	iconst_0
	putfield A/a193 I 

	; field initialization: a194
	aload_0
	iconst_0
	putfield A/a194 I 

	; field initialization: a195
	aload_0
	iconst_0
	putfield A/a195 I 

	; field initialization: a196
	aload_0
	iconst_0
	putfield A/a196 I 

	; field initialization: a197
	aload_0
	iconst_0
	putfield A/a197 I 

	; field initialization: a198
	aload_0
	iconst_0
	putfield A/a198 I 

	; field initialization: a199
	aload_0
	iconst_0
	putfield A/a199 I 

	; field initialization: a200
	aload_0
	iconst_0
	putfield A/a200 I 

	; field initialization: a201
	aload_0
	iconst_0
	putfield A/a201 I 

	; field initialization: a202
	aload_0
	iconst_0
	putfield A/a202 I 

	; field initialization: a203
	aload_0
	iconst_0
	putfield A/a203 I 

	; field initialization: a204
	aload_0
	iconst_0
	putfield A/a204 I 

	; field initialization: a205
	aload_0
	iconst_0
	putfield A/a205 I 

	; field initialization: a206
	aload_0
	iconst_0
	putfield A/a206 I 

	; field initialization: a207
	aload_0
	iconst_0
	putfield A/a207 I 

	; field initialization: a208
	aload_0
	iconst_0
	putfield A/a208 I 

	; field initialization: a209
	aload_0
	iconst_0
	putfield A/a209 I 

	; field initialization: a210
	aload_0
	iconst_0
	putfield A/a210 I 

	; field initialization: a211
	aload_0
	iconst_0
	putfield A/a211 I 

	; field initialization: a212
	aload_0
	iconst_0
	putfield A/a212 I 

	; field initialization: a213
	aload_0
	iconst_0
	putfield A/a213 I 

	; field initialization: a214
	aload_0
	iconst_0
	putfield A/a214 I 

	; field initialization: a215
	aload_0
	iconst_0
	putfield A/a215 I 

	; field initialization: a216
	aload_0
	iconst_0
	putfield A/a216 I 

	; field initialization: a217
	aload_0
	iconst_0
	putfield A/a217 I 

	; field initialization: a218
	aload_0
	iconst_0
	putfield A/a218 I 

	; field initialization: a219
	aload_0
	iconst_0
	putfield A/a219 I 

	; field initialization: a220
	aload_0
	iconst_0
	putfield A/a220 I 

	; field initialization: a221
	aload_0
	iconst_0
	putfield A/a221 I 

	; field initialization: a222
	aload_0
	iconst_0
	putfield A/a222 I 

	; field initialization: a223
	aload_0
	iconst_0
	putfield A/a223 I 

	; field initialization: a224
	aload_0
	iconst_0
	putfield A/a224 I 

	; field initialization: a225
	aload_0
	iconst_0
	putfield A/a225 I 

	; field initialization: a226
	aload_0
	iconst_0
	putfield A/a226 I 

	; field initialization: a227
	aload_0
	iconst_0
	putfield A/a227 I 

	; field initialization: a228
	aload_0
	iconst_0
	putfield A/a228 I 

	; field initialization: a229
	aload_0
	iconst_0
	putfield A/a229 I 

	; field initialization: a230
	aload_0
	iconst_0
	putfield A/a230 I 

	; field initialization: a231
	aload_0
	iconst_0
	putfield A/a231 I 

	; field initialization: a232
	aload_0
	iconst_0
	putfield A/a232 I 

	; field initialization: a233
	aload_0
	iconst_0
	putfield A/a233 I 

	; field initialization: a234
	aload_0
	iconst_0
	putfield A/a234 I 

	; field initialization: a235
	aload_0
	iconst_0
	putfield A/a235 I 

	; field initialization: a236
	aload_0
	iconst_0
	putfield A/a236 I 

	; field initialization: a237
	aload_0
	iconst_0
	putfield A/a237 I 

	; field initialization: a238
	aload_0
	iconst_0
	putfield A/a238 I 

	; field initialization: a239
	aload_0
	iconst_0
	putfield A/a239 I 

	; field initialization: a240
	aload_0
	iconst_0
	putfield A/a240 I 

	; field initialization: a241
	aload_0
	iconst_0
	putfield A/a241 I 

	; field initialization: a242
	aload_0
	iconst_0
	putfield A/a242 I 

	; field initialization: a243
	aload_0
	iconst_0
	putfield A/a243 I 

	; field initialization: a244
	aload_0
	iconst_0
	putfield A/a244 I 

	; field initialization: a245
	aload_0
	iconst_0
	putfield A/a245 I 

	; field initialization: a246
	aload_0
	iconst_0
	putfield A/a246 I 

	; field initialization: a247
	aload_0
	iconst_0
	putfield A/a247 I 

	; field initialization: a248
	aload_0
	iconst_0
	putfield A/a248 I 

	; field initialization: a249
	aload_0
	iconst_0
	putfield A/a249 I 

	; field initialization: a250
	aload_0
	iconst_0
	putfield A/a250 I 

	; field initialization: a251
	aload_0
	iconst_0
	putfield A/a251 I 

	; field initialization: a252
	aload_0
	iconst_0
	putfield A/a252 I 

	; field initialization: a253
	aload_0
	iconst_0
	putfield A/a253 I 

	; field initialization: a254
	aload_0
	iconst_0
	putfield A/a254 I 

	; field initialization: a255
	aload_0
	iconst_0
	putfield A/a255 I 

	; field initialization: a256
	aload_0
	iconst_0
	putfield A/a256 I 

	; field initialization: a257
	aload_0
	iconst_0
	putfield A/a257 I 

	; field initialization: a258
	aload_0
	iconst_0
	putfield A/a258 I 

	; field initialization: a259
	aload_0
	iconst_0
	putfield A/a259 I 

	; field initialization: a260
	aload_0
	iconst_0
	putfield A/a260 I 

	; field initialization: a261
	aload_0
	iconst_0
	putfield A/a261 I 

	; field initialization: a262
	aload_0
	iconst_0
	putfield A/a262 I 

	; field initialization: a263
	aload_0
	iconst_0
	putfield A/a263 I 

	; field initialization: a264
	aload_0
	iconst_0
	putfield A/a264 I 

	; field initialization: a265
	aload_0
	iconst_0
	putfield A/a265 I 

	; field initialization: a266
	aload_0
	iconst_0
	putfield A/a266 I 

	; field initialization: a267
	aload_0
	iconst_0
	putfield A/a267 I 

	; field initialization: a268
	aload_0
	iconst_0
	putfield A/a268 I 

	; field initialization: a269
	aload_0
	iconst_0
	putfield A/a269 I 

	; field initialization: a270
	aload_0
	iconst_0
	putfield A/a270 I 

	; field initialization: a271
	aload_0
	iconst_0
	putfield A/a271 I 

	; field initialization: a272
	aload_0
	iconst_0
	putfield A/a272 I 

	; field initialization: a273
	aload_0
	iconst_0
	putfield A/a273 I 

	; field initialization: a274
	aload_0
	iconst_0
	putfield A/a274 I 

	; field initialization: a275
	aload_0
	iconst_0
	putfield A/a275 I 

	; field initialization: a276
	aload_0
	iconst_0
	putfield A/a276 I 

	; field initialization: a277
	aload_0
	iconst_0
	putfield A/a277 I 

	; field initialization: a278
	aload_0
	iconst_0
	putfield A/a278 I 

	; field initialization: a279
	aload_0
	iconst_0
	putfield A/a279 I 

	; field initialization: a280
	aload_0
	iconst_0
	putfield A/a280 I 

	; field initialization: a281
	aload_0
	iconst_0
	putfield A/a281 I 

	; field initialization: a282
	aload_0
	iconst_0
	putfield A/a282 I 

	; field initialization: a283
	aload_0
	iconst_0
	putfield A/a283 I 

	; field initialization: a284
	aload_0
	iconst_0
	putfield A/a284 I 

	; field initialization: a285
	aload_0
	iconst_0
	putfield A/a285 I 

	; field initialization: a286
	aload_0
	iconst_0
	putfield A/a286 I 

	; field initialization: a287
	aload_0
	iconst_0
	putfield A/a287 I 

	; field initialization: a288
	aload_0
	iconst_0
	putfield A/a288 I 

	; field initialization: a289
	aload_0
	iconst_0
	putfield A/a289 I 

	; field initialization: a290
	aload_0
	iconst_0
	putfield A/a290 I 

	; field initialization: a291
	aload_0
	iconst_0
	putfield A/a291 I 

	; field initialization: a292
	aload_0
	iconst_0
	putfield A/a292 I 

	; field initialization: a293
	aload_0
	iconst_0
	putfield A/a293 I 

	; field initialization: a294
	aload_0
	iconst_0
	putfield A/a294 I 

	; field initialization: a295
	aload_0
	iconst_0
	putfield A/a295 I 

	; field initialization: a296
	aload_0
	iconst_0
	putfield A/a296 I 

	; field initialization: a297
	aload_0
	iconst_0
	putfield A/a297 I 

	; field initialization: a298
	aload_0
	iconst_0
	putfield A/a298 I 

	; field initialization: a299
	aload_0
	iconst_0
	putfield A/a299 I 

	; field initialization: a300
	aload_0
	iconst_0
	putfield A/a300 I 

	; field initialization: a301
	aload_0
	iconst_0
	putfield A/a301 I 

	; field initialization: a302
	aload_0
	iconst_0
	putfield A/a302 I 

	; field initialization: a303
	aload_0
	iconst_0
	putfield A/a303 I 

	; field initialization: a304
	aload_0
	iconst_0
	putfield A/a304 I 

	; field initialization: a305
	aload_0
	iconst_0
	putfield A/a305 I 

	; field initialization: a306
	aload_0
	iconst_0
	putfield A/a306 I 

	; field initialization: a307
	aload_0
	iconst_0
	putfield A/a307 I 

	; field initialization: a308
	aload_0
	iconst_0
	putfield A/a308 I 

	; field initialization: a309
	aload_0
	iconst_0
	putfield A/a309 I 

	; field initialization: a310
	aload_0
	iconst_0
	putfield A/a310 I 

	; field initialization: a311
	aload_0
	iconst_0
	putfield A/a311 I 

	; field initialization: a312
	aload_0
	iconst_0
	putfield A/a312 I 

	; field initialization: a313
	aload_0
	iconst_0
	putfield A/a313 I 

	; field initialization: a314
	aload_0
	iconst_0
	putfield A/a314 I 

	; field initialization: a315
	aload_0
	iconst_0
	putfield A/a315 I 

	; field initialization: a316
	aload_0
	iconst_0
	putfield A/a316 I 

	; field initialization: a317
	aload_0
	iconst_0
	putfield A/a317 I 

	; field initialization: a318
	aload_0
	iconst_0
	putfield A/a318 I 

	; field initialization: a319
	aload_0
	iconst_0
	putfield A/a319 I 

	; field initialization: a320
	aload_0
	iconst_0
	putfield A/a320 I 

	; field initialization: a321
	aload_0
	iconst_0
	putfield A/a321 I 

	; field initialization: a322
	aload_0
	iconst_0
	putfield A/a322 I 

	; field initialization: a323
	aload_0
	iconst_0
	putfield A/a323 I 

	; field initialization: a324
	aload_0
	iconst_0
	putfield A/a324 I 

	; field initialization: a325
	aload_0
	iconst_0
	putfield A/a325 I 

	; field initialization: a326
	aload_0
	iconst_0
	putfield A/a326 I 

	; field initialization: a327
	aload_0
	iconst_0
	putfield A/a327 I 

	; field initialization: a328
	aload_0
	iconst_0
	putfield A/a328 I 

	; field initialization: a329
	aload_0
	iconst_0
	putfield A/a329 I 

	; field initialization: a330
	aload_0
	iconst_0
	putfield A/a330 I 

	; field initialization: a331
	aload_0
	iconst_0
	putfield A/a331 I 

	; field initialization: a332
	aload_0
	iconst_0
	putfield A/a332 I 

	; field initialization: a333
	aload_0
	iconst_0
	putfield A/a333 I 

	; field initialization: a334
	aload_0
	iconst_0
	putfield A/a334 I 

	; field initialization: a335
	aload_0
	iconst_0
	putfield A/a335 I 

	; field initialization: a336
	aload_0
	iconst_0
	putfield A/a336 I 

	; field initialization: a337
	aload_0
	iconst_0
	putfield A/a337 I 

	; field initialization: a338
	aload_0
	iconst_0
	putfield A/a338 I 

	; field initialization: a339
	aload_0
	iconst_0
	putfield A/a339 I 

	; field initialization: a340
	aload_0
	iconst_0
	putfield A/a340 I 

	; field initialization: a341
	aload_0
	iconst_0
	putfield A/a341 I 

	; field initialization: a342
	aload_0
	iconst_0
	putfield A/a342 I 

	; field initialization: a343
	aload_0
	iconst_0
	putfield A/a343 I 

	; field initialization: a344
	aload_0
	iconst_0
	putfield A/a344 I 

	; field initialization: a345
	aload_0
	iconst_0
	putfield A/a345 I 

	; field initialization: a346
	aload_0
	iconst_0
	putfield A/a346 I 

	; field initialization: a347
	aload_0
	iconst_0
	putfield A/a347 I 

	; field initialization: a348
	aload_0
	iconst_0
	putfield A/a348 I 

	; field initialization: a349
	aload_0
	iconst_0
	putfield A/a349 I 

	; field initialization: a350
	aload_0
	iconst_0
	putfield A/a350 I 

	; field initialization: a351
	aload_0
	iconst_0
	putfield A/a351 I 

	; field initialization: a352
	aload_0
	iconst_0
	putfield A/a352 I 

	; field initialization: a353
	aload_0
	iconst_0
	putfield A/a353 I 

	; field initialization: a354
	aload_0
	iconst_0
	putfield A/a354 I 

	; field initialization: a355
	aload_0
	iconst_0
	putfield A/a355 I 

	; field initialization: a356
	aload_0
	iconst_0
	putfield A/a356 I 

	; field initialization: a357
	aload_0
	iconst_0
	putfield A/a357 I 

	; field initialization: a358
	aload_0
	iconst_0
	putfield A/a358 I 

	; field initialization: a359
	aload_0
	iconst_0
	putfield A/a359 I 

	; field initialization: a360
	aload_0
	iconst_0
	putfield A/a360 I 

	; field initialization: a361
	aload_0
	iconst_0
	putfield A/a361 I 

	; field initialization: a362
	aload_0
	iconst_0
	putfield A/a362 I 

	; field initialization: a363
	aload_0
	iconst_0
	putfield A/a363 I 

	; field initialization: a364
	aload_0
	iconst_0
	putfield A/a364 I 

	; field initialization: a365
	aload_0
	iconst_0
	putfield A/a365 I 

	; field initialization: a366
	aload_0
	iconst_0
	putfield A/a366 I 

	; field initialization: a367
	aload_0
	iconst_0
	putfield A/a367 I 

	; field initialization: a368
	aload_0
	iconst_0
	putfield A/a368 I 

	; field initialization: a369
	aload_0
	iconst_0
	putfield A/a369 I 

	; field initialization: a370
	aload_0
	iconst_0
	putfield A/a370 I 

	; field initialization: a371
	aload_0
	iconst_0
	putfield A/a371 I 

	; field initialization: a372
	aload_0
	iconst_0
	putfield A/a372 I 

	; field initialization: a373
	aload_0
	iconst_0
	putfield A/a373 I 

	; field initialization: a374
	aload_0
	iconst_0
	putfield A/a374 I 

	; field initialization: a375
	aload_0
	iconst_0
	putfield A/a375 I 

	; field initialization: a376
	aload_0
	iconst_0
	putfield A/a376 I 

	; field initialization: a377
	aload_0
	iconst_0
	putfield A/a377 I 

	; field initialization: a378
	aload_0
	iconst_0
	putfield A/a378 I 

	; field initialization: a379
	aload_0
	iconst_0
	putfield A/a379 I 

	; field initialization: a380
	aload_0
	iconst_0
	putfield A/a380 I 

	; field initialization: a381
	aload_0
	iconst_0
	putfield A/a381 I 

	; field initialization: a382
	aload_0
	iconst_0
	putfield A/a382 I 

	; field initialization: a383
	aload_0
	iconst_0
	putfield A/a383 I 

	; field initialization: a384
	aload_0
	iconst_0
	putfield A/a384 I 

	; field initialization: a385
	aload_0
	iconst_0
	putfield A/a385 I 

	; field initialization: a386
	aload_0
	iconst_0
	putfield A/a386 I 

	; field initialization: a387
	aload_0
	iconst_0
	putfield A/a387 I 

	; field initialization: a388
	aload_0
	iconst_0
	putfield A/a388 I 

	; field initialization: a389
	aload_0
	iconst_0
	putfield A/a389 I 

	; field initialization: a390
	aload_0
	iconst_0
	putfield A/a390 I 

	; field initialization: a391
	aload_0
	iconst_0
	putfield A/a391 I 

	; field initialization: a392
	aload_0
	iconst_0
	putfield A/a392 I 

	; field initialization: a393
	aload_0
	iconst_0
	putfield A/a393 I 

	; field initialization: a394
	aload_0
	iconst_0
	putfield A/a394 I 

	; field initialization: a395
	aload_0
	iconst_0
	putfield A/a395 I 

	; field initialization: a396
	aload_0
	iconst_0
	putfield A/a396 I 

	; field initialization: a397
	aload_0
	iconst_0
	putfield A/a397 I 

	; field initialization: a398
	aload_0
	iconst_0
	putfield A/a398 I 

	; field initialization: a399
	aload_0
	iconst_0
	putfield A/a399 I 

	; field initialization: a400
	aload_0
	iconst_0
	putfield A/a400 I 

	; field initialization: a401
	aload_0
	iconst_0
	putfield A/a401 I 

	; field initialization: a402
	aload_0
	iconst_0
	putfield A/a402 I 

	; field initialization: a403
	aload_0
	iconst_0
	putfield A/a403 I 

	; field initialization: a404
	aload_0
	iconst_0
	putfield A/a404 I 

	; field initialization: a405
	aload_0
	iconst_0
	putfield A/a405 I 

	; field initialization: a406
	aload_0
	iconst_0
	putfield A/a406 I 

	; field initialization: a407
	aload_0
	iconst_0
	putfield A/a407 I 

	; field initialization: a408
	aload_0
	iconst_0
	putfield A/a408 I 

	; field initialization: a409
	aload_0
	iconst_0
	putfield A/a409 I 

	; field initialization: a410
	aload_0
	iconst_0
	putfield A/a410 I 

	; field initialization: a411
	aload_0
	iconst_0
	putfield A/a411 I 

	; field initialization: a412
	aload_0
	iconst_0
	putfield A/a412 I 

	; field initialization: a413
	aload_0
	iconst_0
	putfield A/a413 I 

	; field initialization: a414
	aload_0
	iconst_0
	putfield A/a414 I 

	; field initialization: a415
	aload_0
	iconst_0
	putfield A/a415 I 

	; field initialization: a416
	aload_0
	iconst_0
	putfield A/a416 I 

	; field initialization: a417
	aload_0
	iconst_0
	putfield A/a417 I 

	; field initialization: a418
	aload_0
	iconst_0
	putfield A/a418 I 

	; field initialization: a419
	aload_0
	iconst_0
	putfield A/a419 I 

	; field initialization: a420
	aload_0
	iconst_0
	putfield A/a420 I 

	; field initialization: a421
	aload_0
	iconst_0
	putfield A/a421 I 

	; field initialization: a422
	aload_0
	iconst_0
	putfield A/a422 I 

	; field initialization: a423
	aload_0
	iconst_0
	putfield A/a423 I 

	; field initialization: a424
	aload_0
	iconst_0
	putfield A/a424 I 

	; field initialization: a425
	aload_0
	iconst_0
	putfield A/a425 I 

	; field initialization: a426
	aload_0
	iconst_0
	putfield A/a426 I 

	; field initialization: a427
	aload_0
	iconst_0
	putfield A/a427 I 

	; field initialization: a428
	aload_0
	iconst_0
	putfield A/a428 I 

	; field initialization: a429
	aload_0
	iconst_0
	putfield A/a429 I 

	; field initialization: a430
	aload_0
	iconst_0
	putfield A/a430 I 

	; field initialization: a431
	aload_0
	iconst_0
	putfield A/a431 I 

	; field initialization: a432
	aload_0
	iconst_0
	putfield A/a432 I 

	; field initialization: a433
	aload_0
	iconst_0
	putfield A/a433 I 

	; field initialization: a434
	aload_0
	iconst_0
	putfield A/a434 I 

	; field initialization: a435
	aload_0
	iconst_0
	putfield A/a435 I 

	; field initialization: a436
	aload_0
	iconst_0
	putfield A/a436 I 

	; field initialization: a437
	aload_0
	iconst_0
	putfield A/a437 I 

	; field initialization: a438
	aload_0
	iconst_0
	putfield A/a438 I 

	; field initialization: a439
	aload_0
	iconst_0
	putfield A/a439 I 

	; field initialization: a440
	aload_0
	iconst_0
	putfield A/a440 I 

	; field initialization: a441
	aload_0
	iconst_0
	putfield A/a441 I 

	; field initialization: a442
	aload_0
	iconst_0
	putfield A/a442 I 

	; field initialization: a443
	aload_0
	iconst_0
	putfield A/a443 I 

	; field initialization: a444
	aload_0
	iconst_0
	putfield A/a444 I 

	; field initialization: a445
	aload_0
	iconst_0
	putfield A/a445 I 

	; field initialization: a446
	aload_0
	iconst_0
	putfield A/a446 I 

	; field initialization: a447
	aload_0
	iconst_0
	putfield A/a447 I 

	; field initialization: a448
	aload_0
	iconst_0
	putfield A/a448 I 

	; field initialization: a449
	aload_0
	iconst_0
	putfield A/a449 I 

	; field initialization: a450
	aload_0
	iconst_0
	putfield A/a450 I 

	; field initialization: a451
	aload_0
	iconst_0
	putfield A/a451 I 

	; field initialization: a452
	aload_0
	iconst_0
	putfield A/a452 I 

	; field initialization: a453
	aload_0
	iconst_0
	putfield A/a453 I 

	; field initialization: a454
	aload_0
	iconst_0
	putfield A/a454 I 

	; field initialization: a455
	aload_0
	iconst_0
	putfield A/a455 I 

	; field initialization: a456
	aload_0
	iconst_0
	putfield A/a456 I 

	; field initialization: a457
	aload_0
	iconst_0
	putfield A/a457 I 

	; field initialization: a458
	aload_0
	iconst_0
	putfield A/a458 I 

	; field initialization: a459
	aload_0
	iconst_0
	putfield A/a459 I 

	; field initialization: a460
	aload_0
	iconst_0
	putfield A/a460 I 

	; field initialization: a461
	aload_0
	iconst_0
	putfield A/a461 I 

	; field initialization: a462
	aload_0
	iconst_0
	putfield A/a462 I 

	; field initialization: a463
	aload_0
	iconst_0
	putfield A/a463 I 

	; field initialization: a464
	aload_0
	iconst_0
	putfield A/a464 I 

	; field initialization: a465
	aload_0
	iconst_0
	putfield A/a465 I 

	; field initialization: a466
	aload_0
	iconst_0
	putfield A/a466 I 

	; field initialization: a467
	aload_0
	iconst_0
	putfield A/a467 I 

	; field initialization: a468
	aload_0
	iconst_0
	putfield A/a468 I 

	; field initialization: a469
	aload_0
	iconst_0
	putfield A/a469 I 

	; field initialization: a470
	aload_0
	iconst_0
	putfield A/a470 I 

	; field initialization: a471
	aload_0
	iconst_0
	putfield A/a471 I 

	; field initialization: a472
	aload_0
	iconst_0
	putfield A/a472 I 

	; field initialization: a473
	aload_0
	iconst_0
	putfield A/a473 I 

	; field initialization: a474
	aload_0
	iconst_0
	putfield A/a474 I 

	; field initialization: a475
	aload_0
	iconst_0
	putfield A/a475 I 

	; field initialization: a476
	aload_0
	iconst_0
	putfield A/a476 I 

	; field initialization: a477
	aload_0
	iconst_0
	putfield A/a477 I 

	; field initialization: a478
	aload_0
	iconst_0
	putfield A/a478 I 

	; field initialization: a479
	aload_0
	iconst_0
	putfield A/a479 I 

	; field initialization: a480
	aload_0
	iconst_0
	putfield A/a480 I 

	; field initialization: a481
	aload_0
	iconst_0
	putfield A/a481 I 

	; field initialization: a482
	aload_0
	iconst_0
	putfield A/a482 I 

	; field initialization: a483
	aload_0
	iconst_0
	putfield A/a483 I 

	; field initialization: a484
	aload_0
	iconst_0
	putfield A/a484 I 

	; field initialization: a485
	aload_0
	iconst_0
	putfield A/a485 I 

	; field initialization: a486
	aload_0
	iconst_0
	putfield A/a486 I 

	; field initialization: a487
	aload_0
	iconst_0
	putfield A/a487 I 

	; field initialization: a488
	aload_0
	iconst_0
	putfield A/a488 I 

	; field initialization: a489
	aload_0
	iconst_0
	putfield A/a489 I 

	; field initialization: a490
	aload_0
	iconst_0
	putfield A/a490 I 

	; field initialization: a491
	aload_0
	iconst_0
	putfield A/a491 I 

	; field initialization: a492
	aload_0
	iconst_0
	putfield A/a492 I 

	; field initialization: a493
	aload_0
	iconst_0
	putfield A/a493 I 

	; field initialization: a494
	aload_0
	iconst_0
	putfield A/a494 I 

	; field initialization: a495
	aload_0
	iconst_0
	putfield A/a495 I 

	; field initialization: a496
	aload_0
	iconst_0
	putfield A/a496 I 

	; field initialization: a497
	aload_0
	iconst_0
	putfield A/a497 I 

	; field initialization: a498
	aload_0
	iconst_0
	putfield A/a498 I 

	; field initialization: a499
	aload_0
	iconst_0
	putfield A/a499 I 
	return
.end method

.method static public main([Ljava.lang.String;)V
	.limit stack 2
	.limit locals 1
	new Main
	dup
	invokespecial Main/<init>()V
	invokevirtual Main/original_main()V
	return
.end method


